CHANGELOG.md
LICENSE
README.md
fettler/__init__.py
fettler/cli.py
fettler/constants.py
fettler/consumer.py
fettler/producer.py
fettler/utils.py
fettler-0.1.0.dist-info/entry_points.txt
fettler-0.1.0.dist-info/LICENSE
fettler-0.1.0.dist-info/WHEEL
fettler-0.1.0.dist-info/METADATA
fettler-0.1.0.dist-info/RECORD
