Metadata-Version: 2.1
Name: fettler
Version: 0.1.0
Summary: Auto refresh cache of redis with MySQL binlog
Home-page: https://github.com/long2ice/fettler
License: Apache-2.0
Keywords: redis,cache,mysql,binlog
Author: long2ice
Author-email: long2ice@gmail.com
Requires-Python: >=3.7,<4.0
Classifier: License :: OSI Approved :: Apache Software License
Classifier: Programming Language :: Python :: 3
Classifier: Programming Language :: Python :: 3.7
Classifier: Programming Language :: Python :: 3.8
Classifier: Programming Language :: Python :: 3.9
Requires-Dist: aioredis
Requires-Dist: asyncmy
Requires-Dist: ciso8601
Requires-Dist: click
Requires-Dist: dynaconf
Requires-Dist: loguru
Project-URL: Documentation, https://github.com/long2ice/fettler
Project-URL: Repository, https://github.com/long2ice/fettler.git
